basestamp/__init__.py
basestamp/client.py
basestamp/merkle.py
basestamp/types.py
basestamp-0.0.1.dist-info/licenses/LICENSE
basestamp-0.0.1.dist-info/METADATA
basestamp-0.0.1.dist-info/WHEEL
basestamp-0.0.1.dist-info/top_level.txt
basestamp-0.0.1.dist-info/RECORD
